dodo_git_commands/__init__.py
dodo_git_commands/chown-src.py
dodo_git_commands/git-multi-branch.py
dodo_git_commands/git-multi-status.py
dodo_git_commands/git-tag.py
dodo_git_commands/git-toggle-hook.py
dodo_git_commands-0.4.1.dist-info/LICENSE
dodo_git_commands-0.4.1.dist-info/METADATA
dodo_git_commands-0.4.1.dist-info/WHEEL
dodo_git_commands-0.4.1.dist-info/top_level.txt
dodo_git_commands-0.4.1.dist-info/RECORD
